nvprof/__init__.py
nvprof/__main__.py
nvprof-0.2.dist-info/DESCRIPTION.rst
nvprof-0.2.dist-info/METADATA
nvprof-0.2.dist-info/RECORD
nvprof-0.2.dist-info/WHEEL
nvprof-0.2.dist-info/entry_points.txt
nvprof-0.2.dist-info/metadata.json
nvprof-0.2.dist-info/top_level.txt
